reusables/__init__.py
reusables/cli.py
reusables/default_list.py
reusables/dt.py
reusables/file_operations.py
reusables/log.py
reusables/namespace.py
reusables/other.py
reusables/process_helpers.py
reusables/sanitizers.py
reusables/shared_variables.py
reusables/string_manipulation.py
reusables/tasker.py
reusables/web.py
reusables/wrappers.py
reusables-1.0.0.dist-info/licenses/AUTHORS.rst
reusables-1.0.0.dist-info/licenses/LICENSE
reusables-1.0.0.dist-info/METADATA
reusables-1.0.0.dist-info/WHEEL
reusables-1.0.0.dist-info/top_level.txt
reusables-1.0.0.dist-info/RECORD
