Metadata-Version: 2.4
Name: reusables
Version: 1.0.0
Summary: Commonly Consumed Code Commodities
Author-email: Chris Griffith <chris@cdgriffith.com>
License-Expression: MIT
Project-URL: Homepage, https://github.com/cdgriffith/Reusables
Classifier: Development Status :: 4 - Beta
Classifier: Environment :: Web Environment
Classifier: Intended Audience :: Developers
Classifier: Intended Audience :: System Administrators
Classifier: Natural Language :: English
Classifier: Operating System :: OS Independent
Classifier: Programming Language :: Python
Classifier: Programming Language :: Python :: 3
Classifier: Programming Language :: Python :: 3.9
Classifier: Programming Language :: Python :: 3.10
Classifier: Programming Language :: Python :: 3.11
Classifier: Programming Language :: Python :: 3.12
Classifier: Programming Language :: Python :: 3.13
Classifier: Programming Language :: Python :: Implementation :: CPython
Classifier: Programming Language :: Python :: Implementation :: PyPy
Classifier: Topic :: Documentation :: Sphinx
Classifier: Topic :: Software Development
Classifier: Topic :: Software Development :: Libraries :: Python Modules
Classifier: Topic :: System :: Archiving
Classifier: Topic :: System :: Archiving :: Compression
Classifier: Topic :: System :: Filesystems
Classifier: Topic :: System :: Logging
Classifier: Topic :: Utilities
Requires-Python: >3.8
License-File: LICENSE
License-File: AUTHORS.rst
Dynamic: license-file
